clip_server/__init__.py
clip_server/__main__.py
clip_server/helper.py
clip_server/onnx-flow.yml
clip_server/tensorrt-flow.yml
clip_server/torch-flow.yml
clip_server/executors/__init__.py
clip_server/executors/clip_onnx.py
clip_server/executors/clip_tensorrt.py
clip_server/executors/clip_torch.py
clip_server/executors/helper.py
clip_server/model/__init__.py
clip_server/model/clip.py
clip_server/model/clip_model.py
clip_server/model/clip_onnx.py
clip_server/model/clip_trt.py
clip_server/model/flash_attention.py
clip_server/model/mclip_model.py
clip_server/model/model.py
clip_server/model/openclip_model.py
clip_server/model/pretrained_models.py
clip_server/model/simple_tokenizer.py
clip_server/model/tokenization.py
clip_server/model/trt_utils.py
clip_server/resources/bpe_simple_vocab_16e6.txt.gz
v_clip_server-0.0.0.dist-info/METADATA
v_clip_server-0.0.0.dist-info/WHEEL
v_clip_server-0.0.0.dist-info/top_level.txt
v_clip_server-0.0.0.dist-info/RECORD
