Metadata-Version: 2.1
Name: v-clip-server
Version: 0.0.0
Summary: Embed images and sentences into fixed-length vectors via CLIP
Home-page: https://github.com/jina-ai/clip-as-service
Download-URL: https://github.com/jina-ai/clip-as-service/tags
Author: Jina AI
Author-email: hello@jina.ai
License: Apache 2.0
Project-URL: Documentation, https://clip-as-service.jina.ai
Project-URL: Source, https://github.com/jina-ai/clip-as-service/
Project-URL: Tracker, https://github.com/jina-ai/clip-as-service/issues
Keywords: jina openai clip deep-learning cross-modal multi-modal neural-search
Classifier: Development Status :: 5 - Production/Stable
Classifier: Intended Audience :: Developers
Classifier: Intended Audience :: Education
Classifier: Intended Audience :: Science/Research
Classifier: Programming Language :: Python :: 3.7
Classifier: Programming Language :: Python :: 3.8
Classifier: Programming Language :: Python :: 3.9
Classifier: Programming Language :: Python :: 3.10
Classifier: Programming Language :: Unix Shell
Classifier: Environment :: Console
Classifier: License :: OSI Approved :: Apache Software License
Classifier: Operating System :: OS Independent
Classifier: Topic :: Database :: Database Engines/Servers
Classifier: Topic :: Scientific/Engineering :: Artificial Intelligence
Classifier: Topic :: Internet :: WWW/HTTP :: Indexing/Search
Classifier: Topic :: Scientific/Engineering :: Image Recognition
Classifier: Topic :: Multimedia :: Video
Classifier: Topic :: Scientific/Engineering
Classifier: Topic :: Scientific/Engineering :: Mathematics
Classifier: Topic :: Software Development
Classifier: Topic :: Software Development :: Libraries
Classifier: Topic :: Software Development :: Libraries :: Python Modules
Requires-Dist: ftfy
Requires-Dist: torch
Requires-Dist: regex
Requires-Dist: torchvision
Requires-Dist: jina (>=3.12.0)
Requires-Dist: prometheus-client
Requires-Dist: open-clip-torch (>=2.7.0)
Provides-Extra: flash-attn
Requires-Dist: flash-attn ; extra == 'flash-attn'
Provides-Extra: onnx
Requires-Dist: onnxruntime ; extra == 'onnx'
Requires-Dist: onnx ; extra == 'onnx'
Requires-Dist: onnxruntime-gpu (>=1.8.0) ; extra == 'onnx'
Provides-Extra: search
Requires-Dist: annlite (>=0.3.10) ; extra == 'search'
Provides-Extra: tensorrt
Requires-Dist: nvidia-tensorrt ; extra == 'tensorrt'
Provides-Extra: transformers
Requires-Dist: transformers (>=4.16.2) ; extra == 'transformers'
